hyperstack/__init__.py
hyperstack/deploy_ollama.py
hyperstack/deploy_pytorch.py
hyperstack/hyperstack.py
hyperstack_python-0.1.0.dist-info/LICENSE
hyperstack_python-0.1.0.dist-info/METADATA
hyperstack_python-0.1.0.dist-info/WHEEL
hyperstack_python-0.1.0.dist-info/RECORD
