Metadata-Version: 2.1
Name: hyperstack-python
Version: 0.1.0
Summary: A Python wrapper for the Hyperstack API
Home-page: https://github.com/balancedscorpion/hyperstack-python
License: Apache-2.0
Keywords: api,wrapper,hyperstack,GPU
Author: Jamie Martin
Requires-Python: >=3.8,<4.0
Classifier: Development Status :: 3 - Alpha
Classifier: Intended Audience :: Developers
Classifier: License :: OSI Approved :: Apache Software License
Classifier: Programming Language :: Python :: 3
Classifier: Programming Language :: Python :: 3.8
Classifier: Programming Language :: Python :: 3.9
Classifier: Programming Language :: Python :: 3.10
Classifier: Programming Language :: Python :: 3.11
Classifier: Programming Language :: Python :: 3.12
Project-URL: Repository, https://github.com/balancedscorpion/hyperstack-python
